odoo10_addon_partner_identification_gln-10.0.1.0.0.99.dev1-nspkg.pth
odoo/addons/partner_identification_gln/README.rst
odoo/addons/partner_identification_gln/__init__.py
odoo/addons/partner_identification_gln/__manifest__.py
odoo/addons/partner_identification_gln/data/partner_identification_gln.xml
odoo/addons/partner_identification_gln/i18n/partner_identification_gln.pot
odoo/addons/partner_identification_gln/i18n/sl.po
odoo/addons/partner_identification_gln/models/__init__.py
odoo/addons/partner_identification_gln/models/partner.py
odoo/addons/partner_identification_gln/static/description/icon.svg
odoo/addons/partner_identification_gln/tests/__init__.py
odoo/addons/partner_identification_gln/tests/test_gln.py
odoo10_addon_partner_identification_gln-10.0.1.0.0.99.dev1.dist-info/METADATA
odoo10_addon_partner_identification_gln-10.0.1.0.0.99.dev1.dist-info/WHEEL
odoo10_addon_partner_identification_gln-10.0.1.0.0.99.dev1.dist-info/namespace_packages.txt
odoo10_addon_partner_identification_gln-10.0.1.0.0.99.dev1.dist-info/top_level.txt
odoo10_addon_partner_identification_gln-10.0.1.0.0.99.dev1.dist-info/RECORD
