Metadata-Version: 2.1
Name: odoo10-addon-partner-identification-gln
Version: 10.0.1.0.0.99.dev1
Summary: This addon extends "Partner Identification Numbers" to provide a number category for GLN registration
Home-page: https://www.acsone.eu
Author: Acsone S.A.,Odoo Community Association (OCA)
Author-email: support@odoo-community.org
License: AGPL-3
Platform: UNKNOWN
Classifier: Programming Language :: Python
Classifier: Framework :: Odoo
Classifier: License :: OSI Approved :: GNU Affero General Public License v3
Requires-Python: ~=2.7
Requires-Dist: odoo10-addon-partner-identification
Requires-Dist: odoo (<10.1dev,>=10.0)
Requires-Dist: python-stdnum
